reddit_photo_aggregator/__init__.py
reddit_photo_aggregator/exceptions.py
reddit_photo_aggregator/image.py
reddit_photo_aggregator/image_validator.py
reddit_photo_aggregator/sorting.py
reddit_photo_aggregator/subreddit.py
reddit_photo_aggregator/user_agent.py
reddit_photo_aggregator-1.0.3.dist-info/LICENSE
reddit_photo_aggregator-1.0.3.dist-info/METADATA
reddit_photo_aggregator-1.0.3.dist-info/WHEEL
reddit_photo_aggregator-1.0.3.dist-info/top_level.txt
reddit_photo_aggregator-1.0.3.dist-info/RECORD
