Metadata-Version: 2.1
Name: reddit-photo-aggregator
Version: 1.0.3
Summary: A library to scrape subreddits for images
Author-email: hamolicious <hamolicious@outlook.com>
Project-URL: Homepage, https://github.com/hamolicious/Reddit-Photo-Aggregator
Project-URL: Bug Tracker, https://github.com/hamolicious/Reddit-Photo-Aggregator/issues
Classifier: Programming Language :: Python :: 3
Classifier: License :: OSI Approved :: MIT License
Classifier: Operating System :: OS Independent
Requires-Python: >=3.11
License-File: LICENSE
Requires-Dist: beautifulsoup4 (==4.12.2)
Requires-Dist: requests (==2.31.0)
Requires-Dist: bs4 (==0.0.1)
